toolchain/.gitignore
toolchain/README.md
toolchain/__init__.py
toolchain/__main__.py
toolchain/build.gradle.kts
toolchain/gradle.properties
toolchain/gradlew
toolchain/gradlew.bat
toolchain/local.properties
toolchain/settings.gradle.kts
toolchain/composeApp/build.gradle.kts
toolchain/composeApp/src/androidMain/AndroidManifest.xml
toolchain/composeApp/src/androidMain/kotlin/org/thisisthepy/python/multiplatform/toolchain/MainActivity.kt
toolchain/composeApp/src/androidMain/kotlin/org/thisisthepy/python/multiplatform/toolchain/Platform.android.kt
toolchain/composeApp/src/androidMain/res/drawable/ic_launcher_background.xml
toolchain/composeApp/src/androidMain/res/drawable-v24/ic_launcher_foreground.xml
toolchain/composeApp/src/androidMain/res/mipmap-anydpi-v26/ic_launcher.xml
toolchain/composeApp/src/androidMain/res/mipmap-anydpi-v26/ic_launcher_round.xml
toolchain/composeApp/src/androidMain/res/mipmap-hdpi/ic_launcher.png
toolchain/composeApp/src/androidMain/res/mipmap-hdpi/ic_launcher_round.png
toolchain/composeApp/src/androidMain/res/mipmap-mdpi/ic_launcher.png
toolchain/composeApp/src/androidMain/res/mipmap-mdpi/ic_launcher_round.png
toolchain/composeApp/src/androidMain/res/mipmap-xhdpi/ic_launcher.png
toolchain/composeApp/src/androidMain/res/mipmap-xhdpi/ic_launcher_round.png
toolchain/composeApp/src/androidMain/res/mipmap-xxhdpi/ic_launcher.png
toolchain/composeApp/src/androidMain/res/mipmap-xxhdpi/ic_launcher_round.png
toolchain/composeApp/src/androidMain/res/mipmap-xxxhdpi/ic_launcher.png
toolchain/composeApp/src/androidMain/res/mipmap-xxxhdpi/ic_launcher_round.png
toolchain/composeApp/src/androidMain/res/values/strings.xml
toolchain/composeApp/src/commonMain/composeResources/drawable/compose-multiplatform.xml
toolchain/composeApp/src/commonMain/kotlin/org/thisisthepy/python/multiplatform/toolchain/App.kt
toolchain/composeApp/src/commonMain/kotlin/org/thisisthepy/python/multiplatform/toolchain/Greeting.kt
toolchain_lite-0.0.1.dist-info/licenses/LICENSE
toolchain_lite-0.0.1.dist-info/WHEEL
toolchain_lite-0.0.1.dist-info/METADATA
toolchain_lite-0.0.1.dist-info/RECORD
